LICENSE
README.md
pyproject.toml
setup.cfg
setup.py
src/Pochecker.egg-info/PKG-INFO
src/Pochecker.egg-info/SOURCES.txt
src/Pochecker.egg-info/dependency_links.txt
src/Pochecker.egg-info/entry_points.txt
src/Pochecker.egg-info/requires.txt
src/Pochecker.egg-info/top_level.txt
src/pochecker/__init__.py
src/pochecker/main.py