Metadata-Version: 2.1
Name: Pochecker
Version: 0.1.0
Summary: "a script to remove outdated documents' po files"
Home-page: https://github.com/mmdbaklhi/pochecker
License: MIT
Project-URL: Bug Tracker, https://github.com/mmdbaklhi/pochecker/issues
Keywords: po,localalayze,localize,outdated,pochecker
Classifier: Programming Language :: Python :: 3
Classifier: Programming Language :: Python :: 3.8
Classifier: Programming Language :: Python :: 3.9
Classifier: Programming Language :: Python :: 3.10
Requires-Python: >=3.8
License-File: LICENSE
